JobFunClassifier/__init__.py
JobFunClassifier/model/CCCV_model.bin
JobFunClassifier/model/JobFunClassifier.py
JobFunClassifier/model/__init__.py
JobFunClassifier/processing/data_management.py
JobFunClassifier/processing/preprocessors.py
JobFunClassifier-0.7.1.dist-info/METADATA
JobFunClassifier-0.7.1.dist-info/WHEEL
JobFunClassifier-0.7.1.dist-info/entry_points.txt
JobFunClassifier-0.7.1.dist-info/top_level.txt
JobFunClassifier-0.7.1.dist-info/RECORD
