Metadata-Version: 2.1
Name: JobFunClassifier
Version: 0.7.1
Summary: The JobFunClassifier is a Python package designed for NLP-based job function classification.
Home-page: https://github.com/LULUCHIU/JobFunClassifier.git
Author: LuTing(Tina) Chiu
Author-email: tinachiu.tech@gmail.com
License: The Unlicense
Project-URL: Source, https://github.com/LULUCHIU/JobFunClassifier.git
Classifier: Development Status :: 2 - Pre-Alpha
Classifier: Intended Audience :: Developers
Classifier: Natural Language :: English
Classifier: Programming Language :: Python :: 3.10
Classifier: Programming Language :: Python :: 3.11
Classifier: Topic :: Text Processing
Classifier: Topic :: Utilities
Requires-Python: >= 3.10, <3.12
Requires-Dist: nltk >=3.8
Requires-Dist: numpy >=1.25
Requires-Dist: pandas >=2.0
Requires-Dist: scipy >=1.5.0
Requires-Dist: threadpoolctl >=2.0.0
Requires-Dist: scikit-learn >=1.3
